easy_hmac/__init__.py
easy_hmac/core.py
easy_hmac/exceptions.py
easy_hmac/utils/__init__.py
easy_hmac/utils/http.py
easy_hmac-0.0.6.dist-info/LICENSE
easy_hmac-0.0.6.dist-info/METADATA
easy_hmac-0.0.6.dist-info/WHEEL
easy_hmac-0.0.6.dist-info/top_level.txt
easy_hmac-0.0.6.dist-info/RECORD
