Metadata-Version: 2.1
Name: easy-hmac
Version: 0.0.6
Summary: A python package that creates and verifies HMAC signatures
Home-page: https://github.com/garrethcain/easy-hmac/
Author: Garreth Cain
Author-email: garrethccain@gmail.com
License: MIT
Classifier: Intended Audience :: Developers
Classifier: License :: OSI Approved :: BSD License
Classifier: Operating System :: OS Independent
Classifier: Programming Language :: Python
Classifier: Programming Language :: Python :: 3
Classifier: Programming Language :: Python :: 3 :: Only
Classifier: Topic :: Internet :: WWW/HTTP
Classifier: Topic :: Internet :: WWW/HTTP :: Dynamic Content
Requires-Python: >=3.6
License-File: LICENSE
